pyATK/__init__.py
pyATK/Cmd/__init__.py
pyATK/Cmd/Base/BaseApplication.py
pyATK/Cmd/Base/MissingArgumentException.py
pyATK/Cmd/Base/__init__.py
pyATK/Cmd/Console/Input.py
pyATK/Cmd/Console/InputArgument.py
pyATK/Cmd/Console/InputOption.py
pyATK/Cmd/Console/Output.py
pyATK/Cmd/Console/__init__.py
pyATK/Cmd/Helpers/ArgumentsHelper.py
pyATK/Cmd/Helpers/ColorHelper.py
pyATK/Cmd/Helpers/ProgressHelper.py
pyATK/Cmd/Helpers/TableHelper.py
pyATK/Cmd/Helpers/__init__.py
pyATK/Containers/Stack.py
pyATK/Containers/Utils.py
pyATK/Containers/__init__.py
pyATK/Filesystem/AbstractCommand.py
pyATK/Filesystem/Commands.py
pyATK/Filesystem/Encoding.py
pyATK/Filesystem/Utils.py
pyATK/Filesystem/__init__.py
pyATK/Misc/Crypto.py
pyATK/Misc/Datetime.py
pyATK/Misc/Decorators.py
pyATK/Misc/Info.py
pyATK/Misc/Logger.py
pyATK/Misc/Misc.py
pyATK/Misc/__init__.py
pyATK/Serializers/BufferedJSON.py
pyATK/Serializers/CSVReader.py
pyATK/Serializers/__init__.py
pyATK/Text/RegexHelper.py
pyATK/Text/StringHelper.py
pyATK/Text/__init__.py
pyATK-1.0.0.dist-info/DESCRIPTION.rst
pyATK-1.0.0.dist-info/METADATA
pyATK-1.0.0.dist-info/RECORD
pyATK-1.0.0.dist-info/WHEEL
pyATK-1.0.0.dist-info/metadata.json
pyATK-1.0.0.dist-info/top_level.txt
