Metadata-Version: 2.0
Name: pyATK
Version: 1.0.0
Summary: A Python toolbox for everyday tasks
Home-page: https://github.com/aturki/pyATK
Author: UNKNOWN
Author-email: aliturki.at@gmail.com
License: MIT
Keywords: toolbox python library
Platform: UNKNOWN
